LICENSE
MANIFEST.in
README.rst
setup.py
xtp/changelist.txt
xtp/include/xoms_api_fund_struct.h
xtp/include/xoms_api_struct.h
xtp/include/xquote_api_struct.h
xtp/include/xtp_api_data_type.h
xtp/include/xtp_api_struct.h
xtp/include/xtp_api_struct_common.h
xtp/include/xtp_quote_api.h
xtp/include/xtp_trader_api.h
xtp/linux/libxtpquoteapi.so
xtp/linux/libxtptraderapi.so
xtp/macosx/libxtpquoteapi.dylib
xtp/macosx/libxtptraderapi.dylib
xtp/win64/xtpquoteapi.dll
xtp/win64/xtpquoteapi.lib
xtp/win64/xtptraderapi.dll
xtp/win64/xtptraderapi.lib
xtpwrapper/__init__.py
xtpwrapper/libxtpquoteapi.so
xtpwrapper/libxtptraderapi.so
xtpwrapper/quote.py
xtpwrapper/quote_api.pyx
xtpwrapper/trader.py
xtpwrapper/trader_api.pyx
xtpwrapper/xtp_enum.py
xtpwrapper.egg-info/PKG-INFO
xtpwrapper.egg-info/SOURCES.txt
xtpwrapper.egg-info/dependency_links.txt
xtpwrapper.egg-info/not-zip-safe
xtpwrapper.egg-info/top_level.txt
xtpwrapper/cppheader/quote_wrapper.h
xtpwrapper/cppheader/trader_wrapper.h
xtpwrapper/headers/__init__.pxd
xtpwrapper/headers/xoms_api_fund_struct.pxd
xtpwrapper/headers/xoms_api_struct.pxd
xtpwrapper/headers/xquote_api_struct.pxd
xtpwrapper/headers/xtp_api_data_type.pxd
xtpwrapper/headers/xtp_api_struct_common.pxd
xtpwrapper/headers/xtp_quote_api.pxd
xtpwrapper/headers/xtp_trader_api.pxd
xtpwrapper/xtp_struct/__init__.py
xtpwrapper/xtp_struct/api_fund_struct.py
xtpwrapper/xtp_struct/xoms_struct.py
xtpwrapper/xtp_struct/xquote_struct.py